bio_info/__init__.py
bio_info/affiliations.py
bio_info/api.py
bio_info/cli.py
bio_info/output.py
bio_info/results.csv
bio_info_pubmed-0.1.0.dist-info/LICENSE
bio_info_pubmed-0.1.0.dist-info/METADATA
bio_info_pubmed-0.1.0.dist-info/WHEEL
bio_info_pubmed-0.1.0.dist-info/entry_points.txt
bio_info_pubmed-0.1.0.dist-info/RECORD
