Metadata-Version: 2.3
Name: bio-info-pubmed
Version: 0.1.0
Summary: A tool to fetch research papers with non-academic authors from PubMed
License: Proprietary
Author: Vivek
Author-email: viveksinghcharak004@gmail.com
Requires-Python: >=3.13
Classifier: License :: Other/Proprietary License
Classifier: Programming Language :: Python :: 3
Classifier: Programming Language :: Python :: 3.13
Requires-Dist: biopython (>=1.85,<2.0)
Requires-Dist: pandas (>=2.2.3,<3.0.0)
Requires-Dist: requests (>=2.32.3,<3.0.0)
Requires-Dist: typing-extensions (>=4.12.2,<5.0.0)
